acquisition_ruling_phrase/__init__.py
acquisition_ruling_phrase/__main__.py
acquisition_ruling_phrase/cues.py
acquisition_ruling_phrase/dispositive/ordered.py
acquisition_ruling_phrase/dispositive/phrases.py
acquisition_ruling_phrase/dispositive/wherefore.py
acquisition_ruling_phrase/patterns/__init__.py
acquisition_ruling_phrase/patterns/after_review.py
acquisition_ruling_phrase/patterns/court_acts.py
acquisition_ruling_phrase/patterns/court_admin.py
acquisition_ruling_phrase/patterns/granted_denied.py
acquisition_ruling_phrase/patterns/hence_this.py
acquisition_ruling_phrase/patterns/issue_errors.py
acquisition_ruling_phrase/patterns/issue_resolution.py
acquisition_ruling_phrase/patterns/main_issue.py
acquisition_ruling_phrase/patterns/merit.py
acquisition_ruling_phrase/patterns/resolve_issue.py
acquisition_ruling_phrase/patterns/single_issue.py
acquisition_ruling_phrase/tags/__init__.py
acquisition_ruling_phrase/tags/base.py
acquisition_ruling_phrase/tags/specific.py
acquisition_ruling_phrase/utils.py
acquisition_ruling_phrase-0.3.1.dist-info/LICENSE
acquisition_ruling_phrase-0.3.1.dist-info/WHEEL
acquisition_ruling_phrase-0.3.1.dist-info/METADATA
acquisition_ruling_phrase-0.3.1.dist-info/RECORD
