Metadata-Version: 2.1
Name: acquisition-ruling-phrase
Version: 0.3.1
Summary: Pattern matching common phrases in Supreme Court decisions indicating the start of content with doctrinal value.
License: Proprietary
Author: Marcelino G. Veloso III
Author-email: mars@veloso.one
Requires-Python: >=3.9,<4.0
Classifier: License :: Other/Proprietary License
Classifier: Programming Language :: Python :: 3
Classifier: Programming Language :: Python :: 3.9
Classifier: Programming Language :: Python :: 3.10
Requires-Dist: acquisition-sanitizer (>=0.4.1,<0.5.0)
Requires-Dist: beautifulsoup4 (>=4.10,<5.0)
Requires-Dist: html5lib (>=1.1,<2.0)
